partcad/__init__.py
partcad/ai.py
partcad/ai_feature_file.py
partcad/ai_google.py
partcad/ai_ollama.py
partcad/ai_openai.py
partcad/assembly.py
partcad/assembly_config.py
partcad/assembly_config_manufacturing.py
partcad/assembly_factory.py
partcad/assembly_factory_alias.py
partcad/assembly_factory_assy.py
partcad/assembly_factory_file.py
partcad/cache.py
partcad/cache_hash.py
partcad/cache_shape.py
partcad/config.py
partcad/consts.py
partcad/context.py
partcad/exception.py
partcad/factory.py
partcad/file_factory.py
partcad/file_factory_url.py
partcad/geom.py
partcad/globals.py
partcad/interactive.py
partcad/interface.py
partcad/interface_inherit.py
partcad/logging.py
partcad/logging_ansi_terminal.py
partcad/mating.py
partcad/part.py
partcad/part_config.py
partcad/part_config_manufacturing.py
partcad/part_factory.py
partcad/part_factory_3mf.py
partcad/part_factory_ai_build123d.py
partcad/part_factory_ai_cadquery.py
partcad/part_factory_ai_openscad.py
partcad/part_factory_alias.py
partcad/part_factory_brep.py
partcad/part_factory_build123d.py
partcad/part_factory_cadquery.py
partcad/part_factory_enrich.py
partcad/part_factory_extrude.py
partcad/part_factory_feature_ai.py
partcad/part_factory_file.py
partcad/part_factory_kicad.py
partcad/part_factory_obj.py
partcad/part_factory_python.py
partcad/part_factory_scad.py
partcad/part_factory_step.py
partcad/part_factory_stl.py
partcad/part_factory_sweep.py
partcad/port.py
partcad/project.py
partcad/project_config.py
partcad/project_factory.py
partcad/project_factory_git.py
partcad/project_factory_local.py
partcad/project_factory_tar.py
partcad/provider.py
partcad/provider_config.py
partcad/provider_data_cart.py
partcad/provider_factory.py
partcad/provider_factory_enrich.py
partcad/provider_factory_file.py
partcad/provider_factory_manufacturer.py
partcad/provider_factory_python.py
partcad/provider_factory_store.py
partcad/provider_request.py
partcad/provider_request_avail.py
partcad/provider_request_caps.py
partcad-0.7.135.dist-info/licenses/LICENSE
partcad-0.7.135.dist-info/METADATA
partcad-0.7.135.dist-info/WHEEL
partcad-0.7.135.dist-info/top_level.txt
partcad-0.7.135.dist-info/RECORD
