Metadata-Version: 2.4
Name: partcad
Version: 0.7.135
Summary: Package manager for CAD models and a modelling framework
Author-email: PartCAD <support@partcad.org>
Maintainer-email: PartCAD <support@partcad.org>
License:                                  Apache License
Project-URL: Homepage, https://github.com/partcad/partcad
Project-URL: Issues, https://github.com/partcad/partcad/issues
Keywords: cadquery,build123d,cad,design,openscad,step,stl
Classifier: Programming Language :: Python :: 3
Classifier: License :: OSI Approved :: Apache Software License
Classifier: Operating System :: OS Independent
Requires-Python: <3.13,>=3.10
License-File: LICENSE
Requires-Dist: cadquery-ocp==7.7.2
Requires-Dist: ocpsvg==0.3.4
Requires-Dist: build123d==0.8.0
Requires-Dist: pyyaml>=6.0.1
Requires-Dist: GitPython>=3.1.40
Requires-Dist: ruamel.yaml>=0.18.5
Requires-Dist: packaging>=23.1
Requires-Dist: setuptools
Requires-Dist: jinja2
Requires-Dist: requests
Requires-Dist: aiofiles
Requires-Dist: aiohttp
Requires-Dist: vyper-config==1.2.1
Requires-Dist: sentry-sdk[opentelemetry]==2.22.0
Requires-Dist: async-lru==2.0.4
Requires-Dist: filelock==3.17.0
Requires-Dist: docker>=7.1.0
Requires-Dist: google.generativeai
Requires-Dist: Pillow
Requires-Dist: openai
Requires-Dist: ollama
Dynamic: license-file
